tc.cpython-37m-x86_64-linux-gnu.so
TCAnalysis-1.0.dist-info/top_level.txt
TCAnalysis-1.0.dist-info/entry_points.txt
TCAnalysis-1.0.dist-info/RECORD
TCAnalysis-1.0.dist-info/WHEEL
TCAnalysis-1.0.dist-info/METADATA
TimeCellAnalysis/README.md
TimeCellAnalysis/__main__.py
TimeCellAnalysis/rho-matlab/8-Summary-cropped.png
TimeCellAnalysis/rho-matlab/README.md
TimeCellAnalysis/rho-matlab/profile_nShuffles1.mat
TimeCellAnalysis/rho-matlab/profile.mat
TimeCellAnalysis/rho-matlab/Figure 1-1.png
TimeCellAnalysis/rho-matlab/Mem_Runtime.png
TimeCellAnalysis/rho-matlab/1-Examples.png
TimeCellAnalysis/rho-matlab/profile_nShuffles4.mat
TimeCellAnalysis/rho-matlab/LICENSE
TimeCellAnalysis/rho-matlab/Figure 6-1.png
TimeCellAnalysis/rho-matlab/algoSchematic-Resub-min.png
TimeCellAnalysis/rho-matlab/algoSchematic-1stSub.png
TimeCellAnalysis/rho-matlab/6-SynthPhysiology.png
TimeCellAnalysis/rho-matlab/5-SynthPredictions.png
TimeCellAnalysis/rho-matlab/4-SynthScores.png
TimeCellAnalysis/rho-matlab/profile_nShuffles10.mat
TimeCellAnalysis/rho-matlab/Figure 6-2.png
TimeCellAnalysis/rho-matlab/7-RealPhysiology.png
TimeCellAnalysis/rho-matlab/runtimes.mat
TimeCellAnalysis/TcPy/ground_truth_check.py
TimeCellAnalysis/TcPy/README.md
TimeCellAnalysis/TcPy/ti_demo.py
TimeCellAnalysis/TcPy/timeCellMatlabExample.py
TimeCellAnalysis/TcPy/expt_batch_analysis.py
TimeCellAnalysis/TcPy/run_batch_analysis.m
TimeCellAnalysis/TcPy/tiScore.cpp
TimeCellAnalysis/TcPy/pyBindMat.py
TimeCellAnalysis/TcPy/tcBind.cpp
TimeCellAnalysis/TcPy/run_batch_analysis.py
TimeCellAnalysis/TcPy/benchmark.py
TimeCellAnalysis/TcPy/tcDefaults.cpp
TimeCellAnalysis/TcPy/tcHeader.h
TimeCellAnalysis/TcPy/peq_demo.py
TimeCellAnalysis/TcPy/r2bScore.cpp
TimeCellAnalysis/TcPy/peqScore.cpp
TimeCellAnalysis/TcPy/__init__.py
TimeCellAnalysis/TcPy/timeCell.cpp
TimeCellAnalysis/TcPy/r2b_demo.py
TimeCellAnalysis/TcPy/Makefile
