Metadata-Version: 2.1
Name: TCAnalysis
Version: 1.0
Summary: The code base is to use of timeCell python module on Matlab files
Home-page: http://github.com/bhallalab/timecellanalysis
Author: Upinder S. Bhalla
Author-email: bhalla@ncbs.res.in
Maintainer: HarshaRani
Maintainer-email: hrani@ncbs.res.in
License: GPLv3
Requires-Dist: numpy
Requires-Dist: matplotlib
Requires-Dist: h5py
